pyarccli/__init__.py
pyarccli/__main__.py
pyarccli/cmd_generate_config_file.py
pyarccli/cmd_generate_module.py
pyarccli/default_cmd_datas.py
pyarccli-0.0.7.dist-info/LICENSE
pyarccli-0.0.7.dist-info/METADATA
pyarccli-0.0.7.dist-info/WHEEL
pyarccli-0.0.7.dist-info/entry_points.txt
pyarccli-0.0.7.dist-info/top_level.txt
pyarccli-0.0.7.dist-info/RECORD
