Metadata-Version: 2.1
Name: pyarccli
Version: 0.0.7
Summary: Paquetage Python pour generer des blocs de code pour faciliter la creation d'application
Home-page: https://github.com/inicode_celestin03/pyarccli
Author: INICODE
Author-email: contact.inicode@gmail.com
License: UNKNOWN
Platform: UNKNOWN
Classifier: Programming Language :: Python :: 3
Classifier: License :: OSI Approved :: MIT License
Classifier: Operating System :: OS Independent
Requires-Python: >=3.7
License-File: LICENSE
Requires-Dist: pyarccmder
Requires-Dist: pyarcgenerator
